aogn/__init__.py
aogn/client.py
aogn/settings.py
aogn-0.1.3.dist-info/LICENSE
aogn-0.1.3.dist-info/METADATA
aogn-0.1.3.dist-info/WHEEL
aogn-0.1.3.dist-info/top_level.txt
aogn-0.1.3.dist-info/RECORD
