Metadata-Version: 2.1
Name: aogn
Version: 0.1.3
Summary: Asynchronous APRS OGN (Open Glider Network) Client for asyncio and Python.
Home-page: https://github.com/csindle/aogn
Author: Colin Sindle
Author-email: aogn@succinct.co.za
License: UNKNOWN
Project-URL: Bug Tracker, https://github.com/csindle/aogn/issues
Platform: UNKNOWN
Classifier: Programming Language :: Python :: 3
Classifier: License :: OSI Approved :: GNU Affero General Public License v3 or later (AGPLv3+)
Classifier: Operating System :: OS Independent
Requires-Python: >=3.7
License-File: LICENSE
